{
  "player_id": "camerda01",
  "name": "Daz Cameron",
  "profile_url": "https://www.baseball-reference.com/players/c/camerda01.shtml",
  "scrape_date": "2025-04-19 11:02:19",
  "photo_url": "https://www.baseball-reference.com/req/202412180/images/headshots/d/de4d33e2_mlbam.jpg",
  "positions": "Outfielder",
  "bats_throws": "Bats: Right \u2022 Throws: Right",
  "height_weight": "6-0, 185lb(183cm, 83kg)",
  "team": "Milwaukee Brewers (minors)",
  "born": "January 15, 1997 in McDonough, GA, us"
}