{
  "player_id": "headrbr01",
  "name": "Brent Headrick",
  "profile_url": "https://www.baseball-reference.com/players/h/headrbr01.shtml",
  "scrape_date": "2025-04-19 10:28:57",
  "photo_url": "https://www.baseball-reference.com/req/202412180/images/headshots/9/90760216_mlbam.jpg",
  "positions": "Pitcher",
  "bats_throws": "Bats: Left \u2022 Throws: Left",
  "height_weight": "6-6, 235lb(198cm, 106kg)",
  "team": "New York Yankees (minors, 40-man)",
  "born": "December 17, 1997 in Braidwood, IL, us"
}