{
  "player_id": "norbyco01",
  "name": "Connor Norby",
  "profile_url": "https://www.baseball-reference.com/players/n/norbyco01.shtml",
  "scrape_date": "2025-04-19 10:37:43",
  "photo_url": "https://www.baseball-reference.com/req/202412180/images/headshots/4/43d88135_mlbam.jpg",
  "positions": "Third Baseman and Second Baseman",
  "bats_throws": "Bats: Right \u2022 Throws: Right",
  "height_weight": "5-10, 180lb(178cm, 81kg)",
  "team": "Miami Marlins (majors)",
  "born": "June 8, 2000 in Brooklyn Park, MN, us"
}