{
  "player_id": "ramirha02",
  "name": "Harold Ram\u00edrez",
  "profile_url": "https://www.baseball-reference.com/players/r/ramirha02.shtml",
  "scrape_date": "2025-04-19 11:47:46",
  "photo_url": "https://www.baseball-reference.com/req/202412180/images/headshots/b/b20d8e37_mlbam.jpg",
  "positions": "Outfielder, Designated Hitter and First Baseman",
  "bats_throws": "Bats: Right \u2022 Throws: Right",
  "height_weight": "5-11, 232lb(180cm, 105kg)",
  "born": "September 6, 1994 in Cartagena, Colombiaco"
}