{
  "player_id": "wilsowe01",
  "name": "Weston Wilson",
  "profile_url": "https://www.baseball-reference.com/players/w/wilsowe01.shtml",
  "scrape_date": "2025-04-19 10:48:29",
  "photo_url": "https://www.baseball-reference.com/req/202412180/images/headshots/7/7eaa8a6b_mlbam.jpg",
  "positions": "Leftfielder, Pinch Hitter and Third Baseman",
  "bats_throws": "Bats: Right \u2022 Throws: Right",
  "height_weight": "6-3, 215lb(190cm, 97kg)",
  "team": "Philadelphia Phillies (majors, 10-day IL)",
  "born": "September 11, 1994 in High Point, NC, us"
}