{
  "2025": {
    "WAR": "0.1",
    "AB": "33",
    "H": "8",
    "HR": "0",
    "BA": ".242",
    "R": "1",
    "RBI": "3",
    "SB": "0",
    "OBP": ".286",
    "SLG": ".333",
    "OPS": ".619",
    "OPS+": "83"
  },
  "career": {
    "WAR": "2.4",
    "AB": "1137",
    "H": "242",
    "HR": "57",
    "BA": ".213",
    "R": "124",
    "RBI": "169",
    "SB": "2",
    "OBP": ".256",
    "SLG": ".410",
    "OPS": ".666",
    "OPS+": "82"
  },
  "player_id": "higasky01",
  "name": "Kyle Higashioka",
  "scrape_date": "2025-04-19 10:30:24"
}