{
  "2025": {
    "WAR": "0.2",
    "AB": "76",
    "H": "20",
    "HR": "2",
    "BA": ".263",
    "R": "11",
    "RBI": "8",
    "SB": "2",
    "OBP": ".322",
    "SLG": ".395",
    "OPS": ".717",
    "OPS+": "107"
  },
  "career": {
    "WAR": "50.0",
    "AB": "5518",
    "H": "1512",
    "HR": "250",
    "BA": ".274",
    "R": "905",
    "RBI": "778",
    "SB": "187",
    "OBP": ".341",
    "SLG": ".475",
    "OPS": ".817",
    "OPS+": "119"
  },
  "player_id": "lindofr01",
  "name": "Francisco Lindor",
  "scrape_date": "2025-04-19 10:38:57"
}