{
  "2025": {
    "WAR": "0.2",
    "AB": "20",
    "H": "7",
    "HR": "0",
    "BA": ".350",
    "R": "3",
    "RBI": "1",
    "SB": "2",
    "OBP": ".381",
    "SLG": ".450",
    "OPS": ".831",
    "OPS+": "138"
  },
  "career": {
    "WAR": "2.3",
    "AB": "1183",
    "H": "301",
    "HR": "24",
    "BA": ".254",
    "R": "162",
    "RBI": "125",
    "SB": "21",
    "OBP": ".342",
    "SLG": ".374",
    "OPS": ".715",
    "OPS+": "97"
  },
  "player_id": "refsnro01",
  "name": "Rob Refsnyder",
  "scrape_date": "2025-04-19 11:48:07"
}