{
  "2025": {
    "WAR": "0.8",
    "AB": "52",
    "H": "20",
    "HR": "2",
    "BA": ".385",
    "R": "8",
    "RBI": "10",
    "SB": "2",
    "OBP": ".441",
    "SLG": ".615",
    "OPS": "1.056",
    "OPS+": "204"
  },
  "career": {
    "WAR": "38.3",
    "AB": "5109",
    "H": "1346",
    "HR": "263",
    "BA": ".263",
    "R": "884",
    "RBI": "722",
    "SB": "104",
    "OBP": ".349",
    "SLG": ".471",
    "OPS": ".820",
    "OPS+": "125"
  },
  "player_id": "springe01",
  "name": "George Springer",
  "scrape_date": "2025-04-19 11:57:58"
}