{
  "2025": {
    "WAR": "0.3",
    "AB": "45",
    "H": "14",
    "HR": "0",
    "BA": ".311",
    "R": "7",
    "RBI": "10",
    "SB": "2",
    "OBP": ".373",
    "SLG": ".467",
    "OPS": ".839",
    "OPS+": "137"
  },
  "career": {
    "WAR": "2.7",
    "AB": "895",
    "H": "206",
    "HR": "20",
    "BA": ".230",
    "R": "116",
    "RBI": "105",
    "SB": "19",
    "OBP": ".276",
    "SLG": ".364",
    "OPS": ".640",
    "OPS+": "77"
  },
  "player_id": "thomaal01",
  "name": "Alek Thomas",
  "scrape_date": "2025-04-19 11:17:36"
}