{
  "2025": {
    "WAR": "-0.3",
    "AB": "23",
    "H": "4",
    "HR": "0",
    "BA": ".174",
    "R": "2",
    "RBI": "0",
    "SB": "0",
    "OBP": ".174",
    "SLG": ".217",
    "OPS": ".391",
    "OPS+": "12"
  },
  "career": {
    "WAR": "0.7",
    "AB": "437",
    "H": "99",
    "HR": "13",
    "BA": ".227",
    "R": "58",
    "RBI": "51",
    "SB": "16",
    "OBP": ".300",
    "SLG": ".387",
    "OPS": ".687",
    "OPS+": "88"
  },
  "player_id": "waterdr01",
  "name": "Drew Waters",
  "scrape_date": "2025-04-19 10:47:10"
}